nginx_install/__init__.py
nginx_install/__main__.py
nginx_install/cli.py
nginx_install/config.py
nginx_install/context.py
nginx_install/installers/__init__.py
nginx_install/installers/base.py
nginx_install/installers/brotli.py
nginx_install/installers/core.py
nginx_install/installers/fancyindex.py
nginx_install/installers/general_git.py
nginx_install/installers/geoip2.py
nginx_install/installers/headers_more.py
nginx_install/installers/http_tls_dyn_size.py
nginx_install/installers/ndk.py
nginx_install/installers/openssl.py
nginx_install/installers/subfilter.py
nginx_install/installers/template.py
nginx_install/installers/zlib_cf.py
nginx_install/utils.py
nginx_install-0.1.12.dist-info/LICENSE
nginx_install-0.1.12.dist-info/METADATA
nginx_install-0.1.12.dist-info/WHEEL
nginx_install-0.1.12.dist-info/entry_points.txt
nginx_install-0.1.12.dist-info/RECORD
