Metadata-Version: 2.3
Name: nginx_install
Version: 0.1.12
Summary: Auto Nginx Installation
License: MIT
Keywords: utilities,nginx,automation
Author: VermiIIi0n
Author-email: dungeon.behind0t@icloud.com
Requires-Python: >=3.10,<4.0
Classifier: Development Status :: 4 - Beta
Classifier: Framework :: Pytest
Classifier: Intended Audience :: Developers
Classifier: License :: OSI Approved :: MIT License
Classifier: Operating System :: OS Independent
Classifier: Programming Language :: Python :: 3
Classifier: Programming Language :: Python :: 3.10
Classifier: Programming Language :: Python :: 3.11
Classifier: Programming Language :: Python :: 3.12
Classifier: Programming Language :: Python :: 3.13
Classifier: Programming Language :: Python :: Implementation :: CPython
Classifier: Programming Language :: Python :: Implementation :: PyPy
Classifier: Topic :: Utilities
Classifier: Typing :: Typed
Requires-Dist: beautifulsoup4 (>=4.12.3,<5.0.0)
Requires-Dist: httpx (>=0.27.0,<0.28.0)
Requires-Dist: lxml (>=5.1.0,<6.0.0)
Requires-Dist: pydantic (>=2.6.3,<3.0.0)
Requires-Dist: pyyaml (>=6.0.1,<7.0.0)
Requires-Dist: rich (>=13.7.1,<14.0.0)
Requires-Dist: semantic-version (>=2.10.0,<3.0.0)
Requires-Dist: vermils (>=0.3.6,<0.4.0)
Project-URL: Homepage, https://github.com/VermiIIi0n/nginx_install
Project-URL: Issues, https://github.com/VermiIIi0n/nginx_install/issues
